{
    "sourceFile": ".vscode/settings.json",
    "activeCommit": 0,
    "commits": [
        {
            "activePatchIndex": 0,
            "patches": [
                {
                    "date": 1659191451794,
                    "content": "Index: \n===================================================================\n--- \n+++ \n"
                }
            ],
            "date": 1659191451794,
            "name": "Commit-0",
            "content": "{\n  \"vue3snippets.enable-compile-vue-file-on-did-save-code\": true\n}"
        }
    ]
}